acecord/__init__.py
acecord/bot.py
acecord/errors.py
acecord/ext/__init__.py
acecord/ext/database.py
acecord/ext/json.py
acecord/modules/__init__.py
acecord/modules/colors.py
acecord/modules/emb.py
acecord/modules/modal_io.py
acecord/utils/log.py
acecord/utils/times.py
acecord/utils/utils.py
acecord/utils/ver_check.py
acecord-1.0.1.dist-info/LICENSE
acecord-1.0.1.dist-info/METADATA
acecord-1.0.1.dist-info/WHEEL
acecord-1.0.1.dist-info/top_level.txt
acecord-1.0.1.dist-info/RECORD
