Metadata-Version: 2.1
Name: acecord
Version: 1.0.1
Summary: An easy-to-use extension with batterys for the Pycord library
Author: Ace
License: MIT
Project-URL: GitHub, https://github.com/sqiuwsqjjsxsajisaj/acecord
Keywords: discord,pycord,py-cord
Classifier: Development Status :: 5 - Production/Stable
Classifier: License :: OSI Approved :: MIT License
Classifier: Intended Audience :: Developers
Classifier: Operating System :: OS Independent
Classifier: Topic :: Software Development :: Libraries
Classifier: Topic :: Software Development :: Libraries :: Python Modules
Classifier: Topic :: Utilities
Classifier: Programming Language :: Python :: 3.8
Classifier: Programming Language :: Python :: 3.9
Classifier: Programming Language :: Python :: 3.10
Classifier: Programming Language :: Python :: 3.11
Requires-Python: >=3.8
License-File: LICENSE
Requires-Dist: py-cord
Requires-Dist: colorama
Requires-Dist: aiosqlite
Requires-Dist: aiohttp
Requires-Dist: acecord
